calculate_vif_rsquare.py
calculate_vif_rsquare-1.0.2.dist-info/LICENSE
calculate_vif_rsquare-1.0.2.dist-info/METADATA
calculate_vif_rsquare-1.0.2.dist-info/WHEEL
calculate_vif_rsquare-1.0.2.dist-info/top_level.txt
calculate_vif_rsquare-1.0.2.dist-info/RECORD
