Metadata-Version: 2.1
Name: calculate-vif-rsquare
Version: 1.0.2
Summary: This function will use to calculate VIF and adjusted rsquare within featue columns or indipendent variables.
Home-page: UNKNOWN
Author: Neeraj Bafila
Author-email: neerajbafila@gmail.com
License: MIT
Platform: UNKNOWN
Classifier: License :: OSI Approved :: MIT License
Classifier: Programming Language :: Python :: 3.6
Classifier: Programming Language :: Python :: 3.7
Classifier: Programming Language :: Python :: 3.8
Requires-Python: >=3.6
Requires-Dist: pandas
Requires-Dist: statsmodels
